{
  "seller": [
    {
      "name": "Shaid Afridi",
      "email": "shahidafridi@gmail.com",
      "password": "abc@123",
      "id": 1
    },
    {
      "name": "Huzaifa",
      "email": "huzaifa@gmail.com",
      "password": "abc@123",
      "id": 2
    },
    {
      "name": "Ahmed",
      "password": "abc@123",
      "email": "ahmed@gmail.com",
      "id": 3
    },
    {
      "name": "fahad",
      "password": "abc123@",
      "email": "fahad@test.com",
      "id": 4
    },
    {
      "name": "ghani",
      "password": "abc123@",
      "email": "ghani@test.com",
      "id": 5
    },
    {
      "name": "sam",
      "password": "abc@123",
      "email": "sam@test.com",
      "id": 6
    },
    {
      "name": "bob",
      "password": "abc123@",
      "email": "bob@test.com",
      "id": 7
    },
    {
      "name": "",
      "password": "",
      "email": "",
      "id": 8
    },
    {
      "name": "",
      "password": "",
      "email": "",
      "id": 9
    }
  ]
}